ht_getter/__init__.py
ht_getter/getter.py
ht_getter-0.0.1.dist-info/LICENSE.txt
ht_getter-0.0.1.dist-info/METADATA
ht_getter-0.0.1.dist-info/WHEEL
ht_getter-0.0.1.dist-info/top_level.txt
ht_getter-0.0.1.dist-info/RECORD
